LICENSE
MANIFEST.in
README.rst
setup.cfg
setup.py
kevopaypal.egg-info/PKG-INFO
kevopaypal.egg-info/SOURCES.txt
kevopaypal.egg-info/dependency_links.txt
kevopaypal.egg-info/requires.txt
kevopaypal.egg-info/top_level.txt
paypal/__init__.py
paypal/admin.py
paypal/base.py
paypal/exceptions.py
paypal/gateway.py
paypal/models.py
paypal/express/__init__.py
paypal/express/admin.py
paypal/express/exceptions.py
paypal/express/facade.py
paypal/express/gateway.py
paypal/express/models.py
paypal/express/urls.py
paypal/express/views.py
paypal/express/dashboard/__init__.py
paypal/express/dashboard/apps.py
paypal/express/dashboard/views.py
paypal/express_checkout/__init__.py
paypal/express_checkout/exceptions.py
paypal/express_checkout/facade.py
paypal/express_checkout/gateway.py
paypal/express_checkout/models.py
paypal/express_checkout/urls.py
paypal/express_checkout/views.py
paypal/express_checkout/dashboard/__init__.py
paypal/express_checkout/dashboard/apps.py
paypal/express_checkout/dashboard/views.py
paypal/migrations/0001_initial.py
paypal/migrations/0002_auto_20190412_0732.py
paypal/migrations/0003_expresscheckouttransaction.py
paypal/migrations/0004_auto_20201203_1246.py
paypal/migrations/__init__.py
paypal/payflow/__init__.py
paypal/payflow/admin.py
paypal/payflow/codes.py
paypal/payflow/facade.py
paypal/payflow/gateway.py
paypal/payflow/models.py
paypal/payflow/dashboard/__init__.py
paypal/payflow/dashboard/apps.py
paypal/payflow/dashboard/views.py
paypal/templates/paypal/express/preview.html
paypal/templates/paypal/express/dashboard/transaction_detail.html
paypal/templates/paypal/express/dashboard/transaction_list.html
paypal/templates/paypal/express_checkout/preview.html
paypal/templates/paypal/express_checkout/dashboard/transaction_detail.html
paypal/templates/paypal/express_checkout/dashboard/transaction_list.html
paypal/templates/paypal/payflow/transaction_detail.html
paypal/templates/paypal/payflow/transaction_list.html