Metadata-Version: 2.1
Name: kevopaypal
Version: 2.0.0
Summary: FIX For Integration with PayPal Express, PayPal Payflow Pro and Adaptive Payments for django-oscar
Home-page: https://github.com/django-oscar/django-oscar-paypal
License: BSD
Keywords: Payment,PayPal,Oscar
Platform: linux
Classifier: Development Status :: 4 - Beta
Classifier: Environment :: Web Environment
Classifier: Framework :: Django
Classifier: Intended Audience :: Developers
Classifier: License :: OSI Approved :: BSD License
Classifier: Operating System :: Unix
Classifier: Programming Language :: Python
Classifier: Programming Language :: Python :: 3
Classifier: Programming Language :: Python :: 3.6
Classifier: Programming Language :: Python :: 3.7
Classifier: Topic :: Other/Nonlisted Topic
Provides-Extra: oscar
